embedding/__init__.py
embedding/m3e-small/.gitattributes
embedding/m3e-small/README.md
embedding/m3e-small/config.json
embedding/m3e-small/pytorch_model.bin
embedding/m3e-small/special_tokens_map.json
embedding/m3e-small/tokenizer.json
embedding/m3e-small/tokenizer_config.json
embedding_zh-2023.6.12.10.49.16.dist-info/LICENSE
embedding_zh-2023.6.12.10.49.16.dist-info/METADATA
embedding_zh-2023.6.12.10.49.16.dist-info/WHEEL
embedding_zh-2023.6.12.10.49.16.dist-info/top_level.txt
embedding_zh-2023.6.12.10.49.16.dist-info/RECORD
